sapure/__init__.py
sapure/enums.py
sapure/utils.py
sapure/auth/__init__.py
sapure/auth/exceptions.py
sapure/auth/httpx_backends.py
sapure/services/__init__.py
sapure/services/aservices.py
sapure/services/exceptions.py
sapure/services/factory.py
sapure/services/utils.py
sapure/services/assets_provider/__init__.py
sapure/services/assets_provider/api.py
sapure/services/assets_provider/entities.py
sapure/services/assets_provider/utils.py
sapure/services/auth/__init__.py
sapure/services/auth/api.py
sapure/services/auth/entities.py
sapure/services/base/__init__.py
sapure/services/base/entities.py
sapure/services/base/enums.py
sapure/services/base/service_provider.py
sapure/services/explore/__init__.py
sapure/services/explore/api.py
sapure/services/explore/conditions.py
sapure/services/explore_internal/__init__.py
sapure/services/explore_internal/api.py
sapure/services/filters/__init__.py
sapure/services/filters/jsx_filters.py
sapure/services/item/__init__.py
sapure/services/item/api.py
sapure/services/monolith/__init__.py
sapure/services/monolith/api.py
sapure/services/monolith/entities.py
sapure/services/monolith_internal/__init__.py
sapure/services/monolith_internal/api.py
sapure/services/work_management/__init__.py
sapure/services/work_management/api.py
sapure/services/work_management/entities.py
sapure/services/work_management/enums.py
sa_pure-0.2.17.dist-info/METADATA
sa_pure-0.2.17.dist-info/WHEEL
sa_pure-0.2.17.dist-info/top_level.txt
sa_pure-0.2.17.dist-info/RECORD
