Metadata-Version: 2.4
Name: sa-pure
Version: 0.2.17
Author-email: SuperAnnotate AI <support@superannotate.com>
License: MIT
Keywords: annotation,superannotate,ai
Requires-Python: >=3.9
Requires-Dist: httpx~=0.28
Requires-Dist: hvac~=2.3
Requires-Dist: pydantic~=2.11
Requires-Dist: pydantic-extra-types~=2.10
Requires-Dist: aiofiles~=24.1
Requires-Dist: PyJWT~=2.9.0
